{"Overbyover":[{"Batsmen":{"1220":{"Batsman": "Herschelle Gibbs","Runs": "1"},"3503":{"Batsman": "Morne van Wyk","Runs": "2"}},"Bowlers":{"3346":{"Bowler": "Adam Sanford","Runs": "4"}},"Runs": "5","Wickets": "0"},{"Batsmen":{"3503":{"Batsman": "Morne van Wyk","Runs": "1"},"1220":{"Batsman": "Herschelle Gibbs","Runs": "0","Isout": true},"260":{"Batsman": "Jacques Rudolph","Runs": "0"}},"Bowlers":{"3484":{"Bowler": "Tino Best","Runs": "1"}},"Runs": "5","Wickets": "1"},{"Batsmen":{"3503":{"Batsman": "Morne van Wyk","Runs": "1"},"260":{"Batsman": "Jacques Rudolph","Runs": "5"}},"Bowlers":{"3346":{"Bowler": "Adam Sanford","Runs": "7"}},"Runs": "7","Wickets": "0"},{"Batsmen":{"260":{"Batsman": "Jacques Rudolph","Runs": "0","Isout": true},"3408":{"Batsman": "Martin van Jaarsveld","Runs": "1"},"3503":{"Batsman": "Morne van Wyk","Runs": "0"}},"Bowlers":{"3484":{"Bowler": "Tino Best","Runs": "1"}},"Runs": "1","Wickets": "1"},{"Batsmen":{"3408":{"Batsman": "Martin van Jaarsveld","Runs": "0"},"3503":{"Batsman": "Morne van Wyk","Runs": "6","Isout": true},"2527":{"Batsman": "Jonty Rhodes","Runs": "1"}},"Bowlers":{"3346":{"Bowler": "Adam Sanford","Runs": "7"}},"Runs": "8","Wickets": "1"},{"Batsmen":{"2527":{"Batsman": "Jonty Rhodes","Runs": "1"},"3408":{"Batsman": "Martin van Jaarsveld","Runs": "1"}},"Bowlers":{"3484":{"Bowler": "Tino Best","Runs": "2"}},"Runs": "4","Wickets": "0"},{"Batsmen":{"3408":{"Batsman": "Martin van Jaarsveld","Runs": "2"},"2527":{"Batsman": "Jonty Rhodes","Runs": "1"}},"Bowlers":{"4535":{"Bowler": "Sulieman Benn","Runs": "3"}},"Runs": "3","Wickets": "0"},{"Batsmen":{"3408":{"Batsman": "Martin van Jaarsveld","Runs": "1"},"2527":{"Batsman": "Jonty Rhodes","Runs": "1"}},"Bowlers":{"9797":{"Bowler": "Samuel Badree","Runs": "2"}},"Runs": "2","Wickets": "0"},{"Batsmen":{"2527":{"Batsman": "Jonty Rhodes","Runs": "6"},"3408":{"Batsman": "Martin van Jaarsveld","Runs": "0","Isout": true},"3544":{"Batsman": "Albie Morkel","Runs": "2"}},"Bowlers":{"4535":{"Bowler": "Sulieman Benn","Runs": "8"}},"Runs": "9","Wickets": "1"},{"Batsmen":{"2527":{"Batsman": "Jonty Rhodes","Runs": "2"},"3544":{"Batsman": "Albie Morkel","Runs": "3"}},"Bowlers":{"9797":{"Bowler": "Samuel Badree","Runs": "7"}},"Runs": "7","Wickets": "0"},{"Batsmen":{"3544":{"Batsman": "Albie Morkel","Runs": "1"},"2527":{"Batsman": "Jonty Rhodes","Runs": "5"}},"Bowlers":{"1503":{"Bowler": "Carl Hooper","Runs": "6"}},"Runs": "6","Wickets": "0"},{"Batsmen":{"2527":{"Batsman": "Jonty Rhodes","Runs": "2"},"3544":{"Batsman": "Albie Morkel","Runs": "8"}},"Bowlers":{"9797":{"Bowler": "Samuel Badree","Runs": "10"}},"Runs": "11","Wickets": "0"},{"Batsmen":{"2527":{"Batsman": "Jonty Rhodes","Runs": "13"},"3544":{"Batsman": "Albie Morkel","Runs": "0"}},"Bowlers":{"1503":{"Bowler": "Carl Hooper","Runs": "15"}},"Runs": "15","Wickets": "0"},{"Batsmen":{"3544":{"Batsman": "Albie Morkel","Runs": "12"},"2527":{"Batsman": "Jonty Rhodes","Runs": "1"}},"Bowlers":{"9797":{"Bowler": "Samuel Badree","Runs": "13"}},"Runs": "13","Wickets": "0"},{"Batsmen":{"3544":{"Batsman": "Albie Morkel","Runs": "5"},"2527":{"Batsman": "Jonty Rhodes","Runs": "9"}},"Bowlers":{"1503":{"Bowler": "Carl Hooper","Runs": "15"}},"Runs": "15","Wickets": "0"},{"Batsmen":{"2527":{"Batsman": "Jonty Rhodes","Runs": "6"},"3544":{"Batsman": "Albie Morkel","Runs": "2"}},"Bowlers":{"3484":{"Bowler": "Tino Best","Runs": "8"}},"Runs": "8","Wickets": "0"},{"Batsmen":{"3544":{"Batsman": "Albie Morkel","Runs": "9"},"2527":{"Batsman": "Jonty Rhodes","Runs": "1"}},"Bowlers":{"4535":{"Bowler": "Sulieman Benn","Runs": "10"}},"Runs": "10","Wickets": "0"},{"Batsmen":{"2527":{"Batsman": "Jonty Rhodes","Runs": "3"},"3544":{"Batsman": "Albie Morkel","Runs": "7"}},"Bowlers":{"3346":{"Bowler": "Adam Sanford","Runs": "11"}},"Runs": "11","Wickets": "0"},{"Batsmen":{"3544":{"Batsman": "Albie Morkel","Runs": "5"},"2527":{"Batsman": "Jonty Rhodes","Runs": "1"}},"Bowlers":{"1503":{"Bowler": "Carl Hooper","Runs": "6"}},"Runs": "6","Wickets": "0"}]}